MANIFEST.in
README.markdown
README.rst
setup.cfg
setup.py
postmonkey/__init__.py
postmonkey/exceptions.py
postmonkey/tests.py
postmonkey.egg-info/PKG-INFO
postmonkey.egg-info/SOURCES.txt
postmonkey.egg-info/dependency_links.txt
postmonkey.egg-info/not-zip-safe
postmonkey.egg-info/requires.txt
postmonkey.egg-info/top_level.txt