Metadata-Version: 1.0
Name: postmonkey
Version: 1.0a1
Summary: Python wrapper for Mailchimp API
Home-page: http://python.chromaticleaves.com/docs/postmonkey/
Author: Eric Rasmussen
Author-email: eric@chromaticleaves.com
License: FreeBSD
Keywords: mailchimp
Platform: UNKNOWN
Classifier: Intended Audience :: Developers
Classifier: Programming Language :: Python
Classifier: Programming Language :: Python :: 2.6
Classifier: Programming Language :: Python :: 2.7
